PyBrain3-3.0.4.dist-info/DESCRIPTION.rst
PyBrain3-3.0.4.dist-info/METADATA
PyBrain3-3.0.4.dist-info/RECORD
PyBrain3-3.0.4.dist-info/WHEEL
PyBrain3-3.0.4.dist-info/metadata.json
PyBrain3-3.0.4.dist-info/top_level.txt
pybrain3/__init__.py
pybrain3/utilities.py
pybrain3/auxiliary/__init__.py
pybrain3/auxiliary/gaussprocess.py
pybrain3/auxiliary/gradientdescent.py
pybrain3/auxiliary/kmeans.py
pybrain3/auxiliary/pca.py
pybrain3/datasets/__init__.py
pybrain3/datasets/classification.py
pybrain3/datasets/dataset.py
pybrain3/datasets/importance.py
pybrain3/datasets/reinforcement.py
pybrain3/datasets/sequential.py
pybrain3/datasets/supervised.py
pybrain3/datasets/unsupervised.py
pybrain3/optimization/__init__.py
pybrain3/optimization/hillclimber.py
pybrain3/optimization/neldermead.py
pybrain3/optimization/optimizer.py
pybrain3/optimization/randomsearch.py
pybrain3/optimization/distributionbased/__init__.py
pybrain3/optimization/distributionbased/cmaes.py
pybrain3/optimization/distributionbased/distributionbased.py
pybrain3/optimization/distributionbased/fem.py
pybrain3/optimization/distributionbased/nes.py
pybrain3/optimization/distributionbased/ves.py
pybrain3/optimization/finitedifference/__init__.py
pybrain3/optimization/finitedifference/fd.py
pybrain3/optimization/finitedifference/pgpe.py
pybrain3/optimization/finitedifference/spsa.py
pybrain3/optimization/memetic/__init__.py
pybrain3/optimization/memetic/innerinversememetic.py
pybrain3/optimization/memetic/innermemetic.py
pybrain3/optimization/memetic/inversememetic.py
pybrain3/optimization/memetic/memetic.py
pybrain3/optimization/populationbased/__init__.py
pybrain3/optimization/populationbased/es.py
pybrain3/optimization/populationbased/evolution.py
pybrain3/optimization/populationbased/ga.py
pybrain3/optimization/populationbased/pso.py
pybrain3/optimization/populationbased/coevolution/__init__.py
pybrain3/optimization/populationbased/coevolution/coevolution.py
pybrain3/optimization/populationbased/coevolution/competitivecoevolution.py
pybrain3/optimization/populationbased/coevolution/multipopulationcoevolution.py
pybrain3/optimization/populationbased/multiobjective/__init__.py
