Metadata-Version: 1.0
Name: PyBrain3
Version: 3.0.4
Summary: PyBrain wrapper for Python3
Home-page: https://github.com/AlexProgramm/pybrain3
Author: Alex Permenev
Author-email: permenev.alex@ya.ru
License: UNKNOWN
Platform: UNKNOWN
